pb2dataframe/__init__.py
pb2dataframe/reader.py
pb2dataframe-0.0.0.2.dist-info/LICENSE
pb2dataframe-0.0.0.2.dist-info/METADATA
pb2dataframe-0.0.0.2.dist-info/WHEEL
pb2dataframe-0.0.0.2.dist-info/RECORD
